yee88/__init__.py
yee88/api.py
yee88/backends.py
yee88/backends_helpers.py
yee88/commands.py
yee88/config.py
yee88/config_migrations.py
yee88/config_watch.py
yee88/context.py
yee88/directives.py
yee88/engines.py
yee88/events.py
yee88/ids.py
yee88/lockfile.py
yee88/logging.py
yee88/markdown.py
yee88/model.py
yee88/plugins.py
yee88/presenter.py
yee88/progress.py
yee88/router.py
yee88/runner.py
yee88/runner_bridge.py
yee88/runtime_loader.py
yee88/scheduler.py
yee88/settings.py
yee88/transport.py
yee88/transport_runtime.py
yee88/transports.py
yee88/worktrees.py
yee88/cli/__init__.py
yee88/cli/config.py
yee88/cli/cron.py
yee88/cli/doctor.py
yee88/cli/handoff.py
yee88/cli/init.py
yee88/cli/onboarding_cmd.py
yee88/cli/plugins.py
yee88/cli/reload.py
yee88/cli/run.py
yee88/cli/topic.py
yee88/cron/__init__.py
yee88/cron/manager.py
yee88/cron/models.py
yee88/cron/scheduler.py
yee88/runners/__init__.py
yee88/runners/claude.py
yee88/runners/codex.py
yee88/runners/mock.py
yee88/runners/opencode.py
yee88/runners/pi.py
yee88/runners/run_options.py
yee88/runners/tool_actions.py
yee88/schemas/__init__.py
yee88/schemas/claude.py
yee88/schemas/codex.py
yee88/schemas/opencode.py
yee88/schemas/pi.py
yee88/skills/yee88/SKILL.md
yee88/telegram/__init__.py
yee88/telegram/api_models.py
yee88/telegram/api_schemas.py
yee88/telegram/backend.py
yee88/telegram/bridge.py
yee88/telegram/chat_prefs.py
yee88/telegram/chat_sessions.py
yee88/telegram/client.py
yee88/telegram/client_api.py
yee88/telegram/context.py
yee88/telegram/engine_defaults.py
yee88/telegram/engine_overrides.py
yee88/telegram/files.py
yee88/telegram/loop.py
yee88/telegram/onboarding.py
yee88/telegram/outbox.py
yee88/telegram/parsing.py
yee88/telegram/render.py
yee88/telegram/state_store.py
yee88/telegram/topic_state.py
yee88/telegram/topics.py
yee88/telegram/trigger_mode.py
yee88/telegram/types.py
yee88/telegram/voice.py
yee88/telegram/commands/__init__.py
yee88/telegram/commands/agent.py
yee88/telegram/commands/cancel.py
yee88-0.7.1.dist-info/METADATA
yee88-0.7.1.dist-info/WHEEL
yee88-0.7.1.dist-info/entry_points.txt
yee88-0.7.1.dist-info/licenses/LICENSE
yee88-0.7.1.dist-info/RECORD
