Metadata-Version: 2.4
Name: yee88
Version: 0.7.1
Summary: Telegram bridge for Codex, Claude Code, and other agent CLIs.
Project-URL: Homepage, https://github.com/banteg/yee88
Project-URL: Documentation, https://yee88.dev/
Project-URL: Repository, https://github.com/banteg/yee88
Project-URL: Issues, https://github.com/banteg/yee88/issues
Author: yee.wang
License: MIT License
License-File: LICENSE
Classifier: License :: OSI Approved :: MIT License
Classifier: Operating System :: OS Independent
Classifier: Programming Language :: Python :: 3
Classifier: Programming Language :: Python :: 3 :: Only
Classifier: Programming Language :: Python :: 3.14
Requires-Python: >=3.14
Requires-Dist: anyio>=4.12.0
Requires-Dist: croniter>=2.0.0
Requires-Dist: httpx>=0.28.1
Requires-Dist: markdown-it-py
Requires-Dist: msgspec>=0.20.0
Requires-Dist: openai>=2.15.0
Requires-Dist: pydantic-settings>=2.12.0
Requires-Dist: pydantic>=2.12.5
Requires-Dist: questionary>=2.1.1
Requires-Dist: rich>=14.2.0
Requires-Dist: structlog>=25.5.0
Requires-Dist: sulguk>=0.11.1
Requires-Dist: tomli-w>=1.2.0
Requires-Dist: typer>=0.21.0
Requires-Dist: watchfiles>=0.21.0
